ndx_turner_metadata/spec/ndx-turner-metadata.extensions.yaml
ndx_turner_metadata/spec/ndx-turner-metadata.namespace.yaml
ndx_turner_metadata/__init__.py
ndx_turner_metadata-0.1.0.dist-info/METADATA
ndx_turner_metadata-0.1.0.dist-info/WHEEL
ndx_turner_metadata-0.1.0.dist-info/licenses/LICENSE.txt
ndx_turner_metadata-0.1.0.dist-info/RECORD
