Metadata-Version: 2.1
Name: ndx-turner-metadata
Version: 0.1.0
Summary: The NWB extension for storing Turner lab specific metadata
Author-email: Szonja Weigl <ben.dichter@catalystneuro.com>
License: MIT
License-File: LICENSE.txt
Keywords: NWB,NeurodataWithoutBorders,ndx-extension,nwb-extension
Classifier: Intended Audience :: Developers
Classifier: Intended Audience :: Science/Research
Classifier: License :: OSI Approved :: MIT License
Requires-Dist: hdmf>=3.10.0
Requires-Dist: pynwb>=2.5.0
